vgis_office/__init__.py
vgis_office/vgis_excel/__init__.py
vgis_office/vgis_excel/excelTools.py
vgis_office/vgis_pdf/__init__.py
vgis_office/vgis_pdf/pdfTools.py
vgis_office/vgis_ppt/__init__.py
vgis_office/vgis_ppt/pptTools.py
vgis_office/vgis_txt/__init__.py
vgis_office/vgis_word/__init__.py
vgis_office/vgis_word/wordTools.py
vgis_office/vgis_word/worddir2xls.py
vgis_office-1.1.8.dist-info/METADATA
vgis_office-1.1.8.dist-info/WHEEL
vgis_office-1.1.8.dist-info/top_level.txt
vgis_office-1.1.8.dist-info/RECORD
