Metadata-Version: 2.1
Name: vgis-office
Version: 1.1.8
Summary: A libary for office operator
Home-page: https://github.com/gisfanmachel/vgisOffice
Author: gisfanmachel
Author-email: gisfanmachel@gmail.com
License: UNKNOWN
Keywords: office,setuptools,development
Platform: UNKNOWN
Classifier: Development Status :: 3 - Alpha
Classifier: Intended Audience :: Developers
Classifier: Topic :: Software Development :: Build Tools
Classifier: License :: OSI Approved :: MIT License
Classifier: Programming Language :: Python :: 3
Classifier: Programming Language :: Python :: 3.7
Classifier: Programming Language :: Python :: 3.8
Classifier: Programming Language :: Python :: 3.9
Classifier: Programming Language :: Python :: 3.10
Classifier: Programming Language :: Python :: 3 :: Only
Requires-Python: >=3.7, <4
Requires-Dist: pandas
Requires-Dist: vgis-utils
Requires-Dist: fitz
Requires-Dist: openpyxl
Requires-Dist: python-docx
Requires-Dist: PyMuPDF
Requires-Dist: comtypes
Requires-Dist: frontend
Requires-Dist: loguru
